<?xml version="1.0" encoding="UTF-8"?>
<includes>
    <include name="MovieWidgets">
        <include content="WidgetListBigLandscape">
            <param name="content_path" value="plugin://plugin.video.fen/?name=32458&amp;iconImage=trending&amp;mode=build_movie_list&amp;action=trakt_movies_trending"/>
            <param name="widget_header" value="الشائعة"/>
            <param name="widget_target" value="videos"/>
            <param name="list_id" value="19011"/>
        </include>
        <include content="WidgetListBigLandscape">
            <param name="content_path" value="plugin://plugin.video.fen/?list_name=Latest+4K+Releases&amp;list_type=user_lists&amp;mode=trakt.list.build_trakt_list&amp;slug=latest-4k-releases&amp;user=giladg&amp;name=%D8%A7%D8%AE%D8%B1+%D8%A5%D8%B5%D8%AF%D8%A7%D8%B1%D8%A7%D8%AA+%D8%A7%D9%84%D9%804K&amp;iconImage=flag_4k"/>
            <param name="widget_header" value="اخر إصدارات الـ4K"/>
            <param name="widget_target" value="videos"/>
            <param name="list_id" value="19012"/>
        </include>
        <include content="WidgetListBigLandscape">
            <param name="content_path" value="plugin://plugin.video.fen/?name=32459&amp;iconImage=popular&amp;mode=build_movie_list&amp;action=tmdb_movies_popular"/>
            <param name="widget_header" value="المشهورة"/>
            <param name="widget_target" value="videos"/>
            <param name="list_id" value="19013"/>
        </include>
        <include content="WidgetListBigLandscape">
            <param name="content_path" value="plugin://plugin.video.fen/?mode=trakt.list.build_trakt_list&amp;user=taiseer999&amp;slug=abukareem-c3410a1c-62e2-4230-bd90-078f7f6e1ba9&amp;list_type=liked_lists&amp;list_name=%D9%83%D9%88%D8%B1%D9%8A+%D8%A3%D9%81%D9%84%D8%A7%D9%85++AbuKareem"/>
            <param name="widget_header" value="كوري أفلام  "/>
            <param name="widget_target" value="videos"/>
            <param name="list_id" value="19014"/>
        </include>
        <include content="WidgetListBigLandscape">
            <param name="content_path" value="plugin://plugin.video.fen/?name=32468&amp;iconImage=oscar_winners&amp;mode=build_movie_list&amp;action=imdb_movies_oscar_winners"/>
            <param name="widget_header" value="الفائزة بالأوسكار"/>
            <param name="widget_target" value="videos"/>
            <param name="list_id" value="19015"/>
        </include>
        <include content="WidgetListBigLandscape">
            <param name="content_path" value="plugin://plugin.video.fen/?name=32476&amp;iconImage=player&amp;mode=build_movie_list&amp;action=in_progress_movies"/>
            <param name="widget_header" value="تكملة المشاهدة"/>
            <param name="widget_target" value="videos"/>
            <param name="list_id" value="19016"/>
        </include>
        <include content="WidgetListBigLandscape">
            <param name="content_path" value="plugin://plugin.video.fen/?name=32226&amp;iconImage=watched_recent&amp;mode=build_movie_list&amp;action=recent_watched_movies"/>
            <param name="widget_header" value="تم مشاهدتُها مؤخراً"/>
            <param name="widget_target" value="videos"/>
            <param name="list_id" value="19017"/>
        </include>
        <include content="WidgetListEpisodes">
            <param name="content_path" value="plugin://plugin.video.fen/?name=32470&amp;iconImage=genres&amp;mode=navigator.genres&amp;menu_type=movie"/>
            <param name="widget_header" value="الأصناف"/>
            <param name="widget_target" value="videos"/>
            <param name="list_id" value="19018"/>
        </include>
        <include content="WidgetListEpisodes">
            <param name="content_path" value="plugin://plugin.video.fen/?name=32472&amp;iconImage=calender&amp;mode=navigator.years&amp;menu_type=movie"/>
            <param name="widget_header" value="السنوات"/>
            <param name="widget_target" value="videos"/>
            <param name="list_id" value="19019"/>
        </include>
        <include content="WidgetListEpisodes">
            <param name="content_path" value="plugin://plugin.video.fen/?mode=navigator.build_shortcut_folder_list&amp;name=Movies+Networks&amp;iconImage=folder&amp;shortcut_folder=True&amp;external_list_item=True"/>
            <param name="widget_header" value="شبكات البث"/>
            <param name="widget_target" value="videos"/>
            <param name="list_id" value="19020"/>
        </include>
    </include>
</includes>